LICENSE
MANIFEST.in
README.md
setup.py
smokesignal.py
smokesignal.egg-info/PKG-INFO
smokesignal.egg-info/SOURCES.txt
smokesignal.egg-info/dependency_links.txt
smokesignal.egg-info/top_level.txt