Metadata-Version: 1.1
Name: smokesignal
Version: 0.4
Summary: Simple python event signaling
Home-page: http://www.github.com/shaunduncan/smokesignal/
Author: Shaun Duncan
Author-email: shaun.duncan@gmail.com
License: MIT
Keywords: python event signal signals signaling
Platform: UNKNOWN
Classifier: Development Status :: 4 - Beta
Classifier: License :: OSI Approved :: MIT License
Classifier: Operating System :: OS Independent
Classifier: Programming Language :: Python
Classifier: Programming Language :: Python :: 2
Classifier: Programming Language :: Python :: 2.6
Classifier: Programming Language :: Python :: 2.7
Classifier: Programming Language :: Python :: 3
Classifier: Programming Language :: Python :: 3.2
Classifier: Programming Language :: Python :: 3.3
Classifier: Programming Language :: Python :: Implementation :: PyPy
Classifier: Topic :: Software Development :: Libraries :: Python Modules
Classifier: Topic :: Utilities
